LICENSE
README.md
setup.py
shap_select/__init__.py
shap_select/select.py
shap_select.egg-info/PKG-INFO
shap_select.egg-info/SOURCES.txt
shap_select.egg-info/dependency_links.txt
shap_select.egg-info/requires.txt
shap_select.egg-info/top_level.txt