Metadata-Version: 2.1
Name: shap-select
Version: 0.1.0
Summary: Heuristic for quick feature selection for tabular regression/classification using shapley values
Home-page: https://github.com/transferwise/shap-select
Author: Wise Plc
Keywords: shap-select
Classifier: Programming Language :: Python :: 3 :: Only
Classifier: Programming Language :: Python :: 3.7
Classifier: Programming Language :: Python :: 3.8
Classifier: Programming Language :: Python :: 3.9
Classifier: Programming Language :: Python :: 3.10
Classifier: Programming Language :: Python :: 3.11
Classifier: Programming Language :: Python :: 3.12
Provides-Extra: test
License-File: LICENSE
